K2fov/K2findCampaigns.py
K2fov/K2onSilicon.py
K2fov/__init__.py
K2fov/c9.py
K2fov/definefov.py
K2fov/fields.py
K2fov/fov.py
K2fov/greatcircle.py
K2fov/plot.py
K2fov/projection.py
K2fov/rotate.py
K2fov/rotate2.py
K2fov/version.py
K2fov/data/k2-c9-microlens-region.json
K2fov/data/k2-c9a-late-targets.json
K2fov/data/k2-c9b-late-targets.json
K2fov/data/k2-campaign-parameters.json
K2fov-8.0.1.data/scripts/K2findCampaigns
K2fov-8.0.1.data/scripts/K2findCampaigns-byname
K2fov-8.0.1.data/scripts/K2findCampaigns-csv
K2fov-8.0.1.data/scripts/K2inMicrolensRegion
K2fov-8.0.1.data/scripts/K2onSilicon
K2fov-8.0.1.dist-info/LICENSE
K2fov-8.0.1.dist-info/METADATA
K2fov-8.0.1.dist-info/WHEEL
K2fov-8.0.1.dist-info/top_level.txt
K2fov-8.0.1.dist-info/RECORD
