Metadata-Version: 2.1
Name: K2fov
Version: 8.0.1
Summary: Find which targets are in the field of view of K2
Home-page: https://github.com/KeplerGO/K2fov
Author: Fergal Mullally, Tom Barclay, Geert Barentsen
Author-email: keplergo@mail.arc.nasa.gov
Classifier: Development Status :: 5 - Production/Stable
Classifier: License :: OSI Approved :: MIT License
Classifier: Operating System :: OS Independent
Classifier: Programming Language :: Python :: 2.7
Classifier: Programming Language :: Python :: 3
Classifier: Intended Audience :: Science/Research
Classifier: Topic :: Scientific/Engineering :: Astronomy
License-File: LICENSE
Requires-Dist: numpy>=1.8
